TeraBoxUtility/__init__.py
TeraBoxUtility/main.py
TeraBoxUtility-0.0.1.dist-info/LICENSE
TeraBoxUtility-0.0.1.dist-info/METADATA
TeraBoxUtility-0.0.1.dist-info/WHEEL
TeraBoxUtility-0.0.1.dist-info/top_level.txt
TeraBoxUtility-0.0.1.dist-info/RECORD
