Metadata-Version: 2.1
Name: TeraBoxUtility
Version: 0.0.1
Summary: A python package for save file in TeraBox
Home-page: https://github.com/nguyenThanhDg/TeraBox
Author: Thanh Dung
Author-email: nguyenthanhdungktm@gmail.com
Classifier: Programming Language :: Python :: 3.9
Classifier: Operating System :: OS Independent
Classifier: License :: OSI Approved :: MIT License
License-File: LICENSE
